jett/__about__.py
jett/__init__.py
jett/__main__.py
jett/__types.py
jett/errors.py
jett/models.py
jett/tools.py
jett/utils.py
jett/engine/__abc.py
jett/engine/__init__.py
jett/engine/arrow/__init__.py
jett/engine/arrow/sink/__init__.py
jett/engine/arrow/sink/console.py
jett/engine/arrow/source/__init__.py
jett/engine/arrow/source/files/local.py
jett/engine/arrow/transform/__abc.py
jett/engine/arrow/transform/__init__.py
jett/engine/arrow/transform/functions.py
jett/engine/daft/__init__.py
jett/engine/daft/sink/__init__.py
jett/engine/daft/sink/console.py
jett/engine/daft/source/__init__.py
jett/engine/daft/source/files/local.py
jett/engine/daft/transform/__abc.py
jett/engine/daft/transform/__init__.py
jett/engine/daft/transform/functions.py
jett/engine/dbt/__init__.py
jett/engine/duckdb/__init__.py
jett/engine/duckdb/sink/__init__.py
jett/engine/duckdb/sink/console.py
jett/engine/duckdb/sink/files/__init__.py
jett/engine/duckdb/sink/files/local.py
jett/engine/duckdb/source/__init__.py
jett/engine/duckdb/source/files/__init__.py
jett/engine/duckdb/source/files/local.py
jett/engine/duckdb/source/files/s3.py
jett/engine/duckdb/transform/__abc.py
jett/engine/duckdb/transform/__init__.py
jett/engine/duckdb/transform/__models.py
jett/engine/duckdb/transform/functions.py
jett/engine/polars/__init__.py
jett/engine/polars/utils.py
jett/engine/polars/sink/__init__.py
jett/engine/polars/sink/console.py
jett/engine/polars/sink/iceberg.py
jett/engine/polars/sink/files/__init__.py
jett/engine/polars/sink/files/local.py
jett/engine/polars/source/__init__.py
jett/engine/polars/source/restapi.py
jett/engine/polars/source/sdk.py
jett/engine/polars/source/files/__init__.py
jett/engine/polars/source/files/local.py
jett/engine/polars/transform/__abc.py
jett/engine/polars/transform/__init__.py
jett/engine/polars/transform/functions.py
jett/engine/spark/__init__.py
jett/engine/spark/schema_change.py
jett/engine/spark/sql_parser.py
jett/engine/spark/temp_storage.py
jett-0.0.3.dist-info/METADATA
jett-0.0.3.dist-info/WHEEL
jett-0.0.3.dist-info/entry_points.txt
jett-0.0.3.dist-info/licenses/LICENSE
jett-0.0.3.dist-info/RECORD
