Metadata-Version: 2.4
Name: jett
Version: 0.0.3
Summary: just an engine template tool
Project-URL: Homepage, https://github.com/ddeutils/jett/
Project-URL: Source Code, https://github.com/ddeutils/jett/
License-File: LICENSE
Requires-Python: >=3.10
Requires-Dist: click>=8.0.0
Requires-Dist: ddeutil-io[toml,yaml]>=0.2.17
Requires-Dist: pyarrow<22.0.0,>=21.0.0
Requires-Dist: pydantic>=2.9.2
Requires-Dist: python-dateutil
Requires-Dist: requests>=2.30.0
Provides-Extra: airflow
Requires-Dist: apache-airflow==2.9.3; extra == 'airflow'
Provides-Extra: daft
Requires-Dist: daft==0.5.21; extra == 'daft'
Provides-Extra: dev
Requires-Dist: clishelf>=0.2.22; extra == 'dev'
Requires-Dist: coverage>=7.10.0; extra == 'dev'
Requires-Dist: pre-commit>=4.0.0; extra == 'dev'
Requires-Dist: pytest>=8.4.0; extra == 'dev'
Requires-Dist: python-dotenv==1.1.1; extra == 'dev'
Provides-Extra: duckdb
Requires-Dist: duckdb==1.3.2; extra == 'duckdb'
Provides-Extra: polars
Requires-Dist: polars==1.32.0; extra == 'polars'
Requires-Dist: pyiceberg==0.9.1; extra == 'polars'
Provides-Extra: spark
Requires-Dist: pyarrow==21.0.0; extra == 'spark'
Requires-Dist: pyspark[connect]==3.4.1; extra == 'spark'
